<?xml version="1.0" encoding="UTF-8"?><ClinicalDocument xmlns="urn:hl7-org:v3" xmlns:sdtc="urn:hl7-org:sdtc" xmlns:xsi="http://www.w3.org/2001/XMLSchema-instance" xsi:schemaLocation="urn:hl7-org:v3 http://xreg2.nist.gov:8080/hitspValidation/schema/cdar2c32/infrastructure/cda/C32_CDA.xsd">  <realmCode code="US"/>  <typeId root="2.16.840.1.113883.1.3" extension="POCD_HD000040"/>  <templateId root="2.16.840.1.113883.10.20.22.1.1" extension="2015-08-01"/>  <templateId root="2.16.840.1.113883.10.20.22.1.2" extension="2015-08-01"/>  <id root="2.16.840.1.113883.19.5" extension="80ca3294-65fd-8fa6-779a-0ca77297ba87" assigningAuthorityName="https://github.com/synthetichealth/synthea"/>  <code code="34133-9" displayName="Summarization of episode note" codeSystem="2.16.840.1.113883.6.1" codeSystemName="LOINC"/>  <title>C-CDA R2.1 Patient Record: Deanna833 Streich926</title>  <effectiveTime value="20250801005609"/>  <confidentialityCode code="N"/>  <languageCode code="en-US"/>  <recordTarget>    <patientRole>      <id root="2.16.840.1.113883.19.5" extension="80ca3294-65fd-8fa6-779a-0ca77297ba87" assigningAuthorityName="https://github.com/synthetichealth/synthea"/>      <addr use="HP">        <streetAddressLine>939 Kemmer Path Unit 82</streetAddressLine>        <city>Buffalo</city>        <state>New York</state>        <postalCode>14222</postalCode>      </addr>      <telecom nullFlavor="NI"/>      <patient>        <name>          <given>Deanna833</given>          <family>Streich926</family>        </name>        <administrativeGenderCode code="F" codeSystem="2.16.840.1.113883.5.1" codeSystemName="HL7 AdministrativeGender"/>        <birthTime value="20021108005609"/>        <raceCode code="2106-3" displayName="white" codeSystemName="CDC Race and Ethnicity" codeSystem="2.16.840.1.113883.6.238"/>        <ethnicGroupCode code="2186-5" displayName="non-hispanic" codeSystemName="CDC Race and Ethnicity" codeSystem="2.16.840.1.113883.6.238"/>        <languageCommunication>          <languageCode code="en-US"/>        </languageCommunication>      </patient>    </patientRole>  </recordTarget>  <author>    <time value="20250801005609"/>    <assignedAuthor>      <id nullFlavor="NA"/>      <addr nullFlavor="NA" />      <telecom nullFlavor="NA" />      <assignedAuthoringDevice>        <manufacturerModelName>https://github.com/synthetichealth/synthea</manufacturerModelName>        <softwareName>https://github.com/synthetichealth/synthea</softwareName>      </assignedAuthoringDevice>      <representedOrganization>        <id nullFlavor="NA"/>        <name>NEIGHBORHOOD HEALTH CENTER OF WNY, INC.</name>        <telecom nullFlavor="NA"/>        <addr>          <streetAddressLine>155 LAWN AVE</streetAddressLine>          <city>BUFFALO</city>          <state>NY</state>          <postalCode>142071816</postalCode>        </addr>      </representedOrganization>    </assignedAuthor>  </author>  <custodian>    <assignedCustodian>      <representedCustodianOrganization>        <id nullFlavor="NA"/>        <name>NEIGHBORHOOD HEALTH CENTER OF WNY, INC.</name>        <telecom nullFlavor="NA"/>        <addr>          <streetAddressLine>155 LAWN AVE</streetAddressLine>          <city>BUFFALO</city>          <state>NY</state>          <postalCode>142071816</postalCode>        </addr>      </representedCustodianOrganization>    </assignedCustodian>  </custodian>  <documentationOf>    <serviceEvent classCode="PCPR">      <effectiveTime>        <low value="20021108005609"/>        <high value="20250801005609"/>      </effectiveTime>    </serviceEvent>  </documentationOf>  <component>    <structuredBody><component>  <!--Allergies/Reactions-->  <section>    <templateId root="2.16.840.1.113883.10.20.22.2.6.1" extension="2015-08-01"/>    <!--Allergies/Reactions section template-->    <code code="48765-2" codeSystem="2.16.840.1.113883.6.1" codeSystemName="LOINC" displayName="Allergies"/>    <title>Allergies and Adverse Reactions</title><text>  <table border="1" width="100%">    <thead>      <tr>        <th>Start</th>        <th>Stop</th>        <th>Description</th>        <th>Code</th>      </tr>    </thead>    <tbody>        <tr>          <td>2006-10-02T19:56:09Z</td>          <td></td>          <td ID="allergies-desc-1">Allergic disposition (finding)</td>          <td ID="allergies-code-1">http://snomed.info/sct 609328004</td>        </tr>        <tr>          <td>2006-10-02T19:56:09Z</td>          <td></td>          <td ID="allergies-desc-2">Mold (organism)</td>          <td ID="allergies-code-2">http://snomed.info/sct 84489001</td>        </tr>    </tbody>  </table></text>    <entry typeCode="DRIV">      <act classCode="ACT" moodCode="EVN">        <templateId root="2.16.840.1.113883.10.20.22.4.30"/>        <templateId root="2.16.840.1.113883.10.20.22.4.30" extension="2015-08-01"/>        <!--Allergy act template -->        <id root="85bdd3ca-32c8-384f-5957-83c3561c87f3"/>        <code nullFlavor="NA"/>        <statusCode code="active"/>        <effectiveTime>          <low value="20061002195609"/>        </effectiveTime>        <entryRelationship typeCode="SUBJ" inversionInd="false">          <observation classCode="OBS" moodCode="EVN">            <templateId root="2.16.840.1.113883.10.20.22.4.7"/>            <templateId root="2.16.840.1.113883.10.20.22.4.7" extension="2014-06-09"/>            <id root="9b413c0e-ef6a-1f06-1f1a-bfbb575b493a"/>            <code code="ASSERTION" codeSystem="2.16.840.1.113883.5.4" />            <text>              <reference value="#allergies-desc-1"/>            </text>            <statusCode code="completed"/>            <effectiveTime>              <low value="20061002195609"/>            </effectiveTime>                    <value xsi:type="CD" code="419199007" displayName="Allergy to substance" codeSystem="2.16.840.1.113883.6.96" codeSystemName="SNOMED CT" />            <participant typeCode="CSM">              <participantRole classCode="MANU">                <playingEntity classCode="MMAT">        <code  code="609328004" codeSystem="2.16.840.1.113883.6.96" displayName="Allergic disposition (finding)">          <originalText><reference value="#allergies-desc-1"/></originalText>        </code>                  <name>Allergic disposition (finding)</name>                </playingEntity>              </participantRole>            </participant>          </observation>        </entryRelationship>      </act>    </entry>    <entry typeCode="DRIV">      <act classCode="ACT" moodCode="EVN">        <templateId root="2.16.840.1.113883.10.20.22.4.30"/>        <templateId root="2.16.840.1.113883.10.20.22.4.30" extension="2015-08-01"/>        <!--Allergy act template -->        <id root="2c06754d-c4c8-a792-5fdc-d9592d5e73cd"/>        <code nullFlavor="NA"/>        <statusCode code="active"/>        <effectiveTime>          <low value="20061002195609"/>        </effectiveTime>        <entryRelationship typeCode="SUBJ" inversionInd="false">          <observation classCode="OBS" moodCode="EVN">            <templateId root="2.16.840.1.113883.10.20.22.4.7"/>            <templateId root="2.16.840.1.113883.10.20.22.4.7" extension="2014-06-09"/>            <id root="3882948f-811b-89ee-2e6b-ae7afa070174"/>            <code code="ASSERTION" codeSystem="2.16.840.1.113883.5.4" />            <text>              <reference value="#allergies-desc-2"/>            </text>            <statusCode code="completed"/>            <effectiveTime>              <low value="20061002195609"/>            </effectiveTime>                    <value xsi:type="CD" code="419199007" displayName="Allergy to substance" codeSystem="2.16.840.1.113883.6.96" codeSystemName="SNOMED CT" />            <participant typeCode="CSM">              <participantRole classCode="MANU">                <playingEntity classCode="MMAT">        <code  code="84489001" codeSystem="2.16.840.1.113883.6.96" displayName="Mold (organism)">          <originalText><reference value="#allergies-desc-2"/></originalText>        </code>                  <name>Mold (organism)</name>                </playingEntity>              </participantRole>            </participant>          </observation>        </entryRelationship>      </act>    </entry>  </section></component><component>  <!--Medications-->  <section>	<templateId root="2.16.840.1.113883.10.20.22.2.1.1" extension="2014-06-09"/>    <code code="10160-0" displayName="History of medication use" codeSystem="2.16.840.1.113883.6.1" codeSystemName="LOINC"/>    <title>Medications</title><text>  <table border="1" width="100%">    <thead>      <tr>        <th>Start</th>        <th>Stop</th>        <th>Description</th>        <th>Code</th>      </tr>    </thead>    <tbody>        <tr>          <td>2006-09-26T00:56:09Z</td>          <td></td>          <td ID="medications-desc-1">Fexofenadine hydrochloride 30 MG Oral Tablet</td>          <td ID="medications-code-1">http://www.nlm.nih.gov/research/umls/rxnorm 997488</td>        </tr>        <tr>          <td>2006-10-02T20:26:20Z</td>          <td></td>          <td ID="medications-desc-2">NDA020800 0.3 ML Epinephrine 1 MG/ML Auto-Injector</td>          <td ID="medications-code-2">http://www.nlm.nih.gov/research/umls/rxnorm 1870230</td>        </tr>        <tr>          <td>2021-10-12T00:56:09Z</td>          <td>2022-10-07T00:56:09Z</td>          <td ID="medications-desc-3">Levora 0.15/30 28 Day Pack</td>          <td ID="medications-code-3">http://www.nlm.nih.gov/research/umls/rxnorm 748879</td>        </tr>        <tr>          <td>2022-10-07T00:56:09Z</td>          <td>2023-10-02T00:56:09Z</td>          <td ID="medications-desc-4">Seasonique 91 Day Pack</td>          <td ID="medications-code-4">http://www.nlm.nih.gov/research/umls/rxnorm 749762</td>        </tr>    </tbody>  </table></text>    <entry>      <!--CCD Medication activity - Required-->      <substanceAdministration classCode="SBADM" moodCode="EVN">        <templateId root="2.16.840.1.113883.10.20.22.4.16"/>        <templateId root="2.16.840.1.113883.10.20.22.4.16" extension="2014-06-09"/>        <id root="8a69b08d-3c35-8d7b-90ea-da2ebf6415a7"/>        <statusCode code="completed"/>        <effectiveTime xsi:type="IVL_TS">          <low value="20060926005609"/>          <high nullFlavor="UNK"/>        </effectiveTime>        <doseQuantity value="1"/>        <consumable>          <!--CCD Product - Required-->          <manufacturedProduct classCode="MANU">            <templateId root="2.16.840.1.113883.10.20.22.4.23"/>            <templateId root="2.16.840.1.113883.10.20.22.4.23" extension="2014-06-09"/>            <manufacturedMaterial>        <code  code="997488" codeSystem="2.16.840.1.113883.6.88" displayName="Fexofenadine hydrochloride 30 MG Oral Tablet">          <originalText><reference value="#medications-desc-1"/></originalText>        </code>              <name>Fexofenadine hydrochloride 30 MG Oral Tablet</name>            </manufacturedMaterial>          </manufacturedProduct>        </consumable>      </substanceAdministration>    </entry>    <entry>      <!--CCD Medication activity - Required-->      <substanceAdministration classCode="SBADM" moodCode="EVN">        <templateId root="2.16.840.1.113883.10.20.22.4.16"/>        <templateId root="2.16.840.1.113883.10.20.22.4.16" extension="2014-06-09"/>        <id root="3484695e-88ba-1b86-2050-0efcdf38167b"/>        <statusCode code="completed"/>        <effectiveTime xsi:type="IVL_TS">          <low value="20061002202620"/>          <high nullFlavor="UNK"/>        </effectiveTime>        <doseQuantity value="1"/>        <consumable>          <!--CCD Product - Required-->          <manufacturedProduct classCode="MANU">            <templateId root="2.16.840.1.113883.10.20.22.4.23"/>            <templateId root="2.16.840.1.113883.10.20.22.4.23" extension="2014-06-09"/>            <manufacturedMaterial>        <code  code="1870230" codeSystem="2.16.840.1.113883.6.88" displayName="NDA020800 0.3 ML Epinephrine 1 MG/ML Auto-Injector">          <originalText><reference value="#medications-desc-2"/></originalText>        </code>              <name>NDA020800 0.3 ML Epinephrine 1 MG/ML Auto-Injector</name>            </manufacturedMaterial>          </manufacturedProduct>        </consumable>      </substanceAdministration>    </entry>    <entry>      <!--CCD Medication activity - Required-->      <substanceAdministration classCode="SBADM" moodCode="EVN">        <templateId root="2.16.840.1.113883.10.20.22.4.16"/>        <templateId root="2.16.840.1.113883.10.20.22.4.16" extension="2014-06-09"/>        <id root="bbbc5e80-83cb-d62e-d89e-858f5fa3c03e"/>        <statusCode code="completed"/>        <effectiveTime xsi:type="IVL_TS">          <low value="20211012005609"/>          <high value="20221007005609"/>        </effectiveTime>        <doseQuantity value="1"/>        <consumable>          <!--CCD Product - Required-->          <manufacturedProduct classCode="MANU">            <templateId root="2.16.840.1.113883.10.20.22.4.23"/>            <templateId root="2.16.840.1.113883.10.20.22.4.23" extension="2014-06-09"/>            <manufacturedMaterial>        <code  code="748879" codeSystem="2.16.840.1.113883.6.88" displayName="Levora 0.15/30 28 Day Pack">          <originalText><reference value="#medications-desc-3"/></originalText>        </code>              <name>Levora 0.15/30 28 Day Pack</name>            </manufacturedMaterial>          </manufacturedProduct>        </consumable>      </substanceAdministration>    </entry>    <entry>      <!--CCD Medication activity - Required-->      <substanceAdministration classCode="SBADM" moodCode="EVN">        <templateId root="2.16.840.1.113883.10.20.22.4.16"/>        <templateId root="2.16.840.1.113883.10.20.22.4.16" extension="2014-06-09"/>        <id root="bee58230-aacb-3dcb-f09f-94f0f5aa9565"/>        <statusCode code="completed"/>        <effectiveTime xsi:type="IVL_TS">          <low value="20221007005609"/>          <high value="20231002005609"/>        </effectiveTime>        <doseQuantity value="1"/>        <consumable>          <!--CCD Product - Required-->          <manufacturedProduct classCode="MANU">            <templateId root="2.16.840.1.113883.10.20.22.4.23"/>            <templateId root="2.16.840.1.113883.10.20.22.4.23" extension="2014-06-09"/>            <manufacturedMaterial>        <code  code="749762" codeSystem="2.16.840.1.113883.6.88" displayName="Seasonique 91 Day Pack">          <originalText><reference value="#medications-desc-4"/></originalText>        </code>              <name>Seasonique 91 Day Pack</name>            </manufacturedMaterial>          </manufacturedProduct>        </consumable>      </substanceAdministration>    </entry>  </section></component><component>  <!--Diagnostic Results-->  <section>    <templateId root="2.16.840.1.113883.10.20.22.2.3.1" extension="2015-08-01"/>    <templateId root="2.16.840.1.113883.10.20.22.2.3.1"/>    <!--Diagnostic Results section template-->    <code code="30954-2" codeSystem="2.16.840.1.113883.6.1" codeSystemName="LOINC" displayName="Results"/>    <title>Diagnostic Results</title><text>  <table border="1" width="100%">    <thead>      <tr>        <th>Start</th>        <th>Stop</th>        <th>Description</th>        <th>Code</th>      </tr>    </thead>    <tbody>        <tr>          <td>2025-01-10T00:56:09Z</td>          <td></td>          <td ID="reports-desc-1">CBC panel - Blood by Automated count</td>          <td ID="reports-code-1">http://loinc.org 58410-2</td>        </tr>        <tr>          <td>2025-01-10T02:11:52Z</td>          <td></td>          <td ID="reports-desc-2">Generalized anxiety disorder 7 item (GAD-7)</td>          <td ID="reports-code-2">http://loinc.org 69737-5</td>        </tr>    </tbody>  </table></text>    <entry typeCode="DRIV">      <organizer classCode="BATTERY" moodCode="EVN">        <templateId root="2.16.840.1.113883.10.20.22.4.1" extension="2015-08-01"/>        <templateId root="2.16.840.1.113883.10.20.22.4.1"/>        <!--Result organizer template -->        <id root="453bb697-3871-c842-aa2a-f9afeb656d7b"/>        <code code="58410-2" codeSystem="2.16.840.1.113883.6.1" codeSystemName="LOINC" displayName="CBC panel - Blood by Automated count"/>        <statusCode code="completed"/>        <effectiveTime>          <low value="20250110005609"/>          <high value="20250110005609"/>        </effectiveTime>        <component>          <observation classCode="OBS" moodCode="EVN">            <templateId root="2.16.840.1.113883.10.20.22.4.2" extension="2015-08-01"/>            <templateId root="2.16.840.1.113883.10.20.22.4.2"/>            <id root="ae897672-9c7d-3ae4-c5af-a3eb0ba8052c"/>        <code  code="6690-2" codeSystem="2.16.840.1.113883.6.1" displayName="Leukocytes [#/volume] in Blood by Automated count">          <originalText><reference value="#reports-desc-1"/></originalText>        </code>            <text>              <reference value="#reports-desc-1"/>            </text>            <statusCode code="completed"/>            <effectiveTime value="20250110005609"/>            <value xsi:type="PQ" value="8.709773612312977" unit="10*3/uL"/>          </observation>        </component>        <component>          <observation classCode="OBS" moodCode="EVN">            <templateId root="2.16.840.1.113883.10.20.22.4.2" extension="2015-08-01"/>            <templateId root="2.16.840.1.113883.10.20.22.4.2"/>            <id root="93eb8e79-7931-5a62-9a5a-0959568bf3a0"/>        <code  code="789-8" codeSystem="2.16.840.1.113883.6.1" displayName="Erythrocytes [#/volume] in Blood by Automated count">          <originalText><reference value="#reports-desc-1"/></originalText>        </code>            <text>              <reference value="#reports-desc-1"/>            </text>            <statusCode code="completed"/>            <effectiveTime value="20250110005609"/>            <value xsi:type="PQ" value="5.030127776740124" unit="10*6/uL"/>          </observation>        </component>        <component>          <observation classCode="OBS" moodCode="EVN">            <templateId root="2.16.840.1.113883.10.20.22.4.2" extension="2015-08-01"/>            <templateId root="2.16.840.1.113883.10.20.22.4.2"/>            <id root="d47cd662-1192-4cce-29dd-70ab7778f80c"/>        <code  code="718-7" codeSystem="2.16.840.1.113883.6.1" displayName="Hemoglobin [Mass/volume] in Blood">          <originalText><reference value="#reports-desc-1"/></originalText>        </code>            <text>              <reference value="#reports-desc-1"/>            </text>            <statusCode code="completed"/>            <effectiveTime value="20250110005609"/>            <value xsi:type="PQ" value="12.93790791217225" unit="g/dL"/>          </observation>        </component>        <component>          <observation classCode="OBS" moodCode="EVN">            <templateId root="2.16.840.1.113883.10.20.22.4.2" extension="2015-08-01"/>            <templateId root="2.16.840.1.113883.10.20.22.4.2"/>            <id root="07cfedff-650a-ed40-c00f-cb983d37db55"/>        <code  code="4544-3" codeSystem="2.16.840.1.113883.6.1" displayName="Hematocrit [Volume Fraction] of Blood by Automated count">          <originalText><reference value="#reports-desc-1"/></originalText>        </code>            <text>              <reference value="#reports-desc-1"/>            </text>            <statusCode code="completed"/>            <effectiveTime value="20250110005609"/>            <value xsi:type="PQ" value="40.13188740542224" unit="%"/>          </observation>        </component>        <component>          <observation classCode="OBS" moodCode="EVN">            <templateId root="2.16.840.1.113883.10.20.22.4.2" extension="2015-08-01"/>            <templateId root="2.16.840.1.113883.10.20.22.4.2"/>            <id root="04508332-5de0-5db8-db38-1b82e02d2e2f"/>        <code  code="787-2" codeSystem="2.16.840.1.113883.6.1" displayName="MCV [Entitic volume] by Automated count">          <originalText><reference value="#reports-desc-1"/></originalText>        </code>            <text>              <reference value="#reports-desc-1"/>            </text>            <statusCode code="completed"/>            <effectiveTime value="20250110005609"/>            <value xsi:type="PQ" value="83.72838102047922" unit="fL"/>          </observation>        </component>        <component>          <observation classCode="OBS" moodCode="EVN">            <templateId root="2.16.840.1.113883.10.20.22.4.2" extension="2015-08-01"/>            <templateId root="2.16.840.1.113883.10.20.22.4.2"/>            <id root="ed325cf1-0d11-32e8-8e9b-e8c47a1bf2ce"/>        <code  code="785-6" codeSystem="2.16.840.1.113883.6.1" displayName="MCH [Entitic mass] by Automated count">          <originalText><reference value="#reports-desc-1"/></originalText>        </code>            <text>              <reference value="#reports-desc-1"/>            </text>            <statusCode code="completed"/>            <effectiveTime value="20250110005609"/>            <value xsi:type="PQ" value="29.804395690397634" unit="pg"/>          </observation>        </component>        <component>          <observation classCode="OBS" moodCode="EVN">            <templateId root="2.16.840.1.113883.10.20.22.4.2" extension="2015-08-01"/>            <templateId root="2.16.840.1.113883.10.20.22.4.2"/>            <id root="b4ed314c-fedd-28ce-aa1a-5aa34440b7fb"/>        <code  code="786-4" codeSystem="2.16.840.1.113883.6.1" displayName="MCHC [Mass/volume] by Automated count">          <originalText><reference value="#reports-desc-1"/></originalText>        </code>            <text>              <reference value="#reports-desc-1"/>            </text>            <statusCode code="completed"/>            <effectiveTime value="20250110005609"/>            <value xsi:type="PQ" value="35.25272419262988" unit="g/dL"/>          </observation>        </component>        <component>          <observation classCode="OBS" moodCode="EVN">            <templateId root="2.16.840.1.113883.10.20.22.4.2" extension="2015-08-01"/>            <templateId root="2.16.840.1.113883.10.20.22.4.2"/>            <id root="a9add63b-4439-e179-4955-1278c1eba297"/>        <code  code="21000-5" codeSystem="2.16.840.1.113883.6.1" displayName="Erythrocyte distribution width [Entitic volume] by Automated count">          <originalText><reference value="#reports-desc-1"/></originalText>        </code>            <text>              <reference value="#reports-desc-1"/>            </text>            <statusCode code="completed"/>            <effectiveTime value="20250110005609"/>            <value xsi:type="PQ" value="44.025572269844396" unit="fL"/>          </observation>        </component>        <component>          <observation classCode="OBS" moodCode="EVN">            <templateId root="2.16.840.1.113883.10.20.22.4.2" extension="2015-08-01"/>            <templateId root="2.16.840.1.113883.10.20.22.4.2"/>            <id root="17a99f14-aa4e-e498-0bbc-98b8e27bb9f2"/>        <code  code="777-3" codeSystem="2.16.840.1.113883.6.1" displayName="Platelets [#/volume] in Blood by Automated count">          <originalText><reference value="#reports-desc-1"/></originalText>        </code>            <text>              <reference value="#reports-desc-1"/>            </text>            <statusCode code="completed"/>            <effectiveTime value="20250110005609"/>            <value xsi:type="PQ" value="320.95184247087536" unit="10*3/uL"/>          </observation>        </component>        <component>          <observation classCode="OBS" moodCode="EVN">            <templateId root="2.16.840.1.113883.10.20.22.4.2" extension="2015-08-01"/>            <templateId root="2.16.840.1.113883.10.20.22.4.2"/>            <id root="3f5ce90f-3d6d-21a2-f648-74cc4afce880"/>        <code  code="32207-3" codeSystem="2.16.840.1.113883.6.1" displayName="Platelet distribution width [Entitic volume] in Blood by Automated count">          <originalText><reference value="#reports-desc-1"/></originalText>        </code>            <text>              <reference value="#reports-desc-1"/>            </text>            <statusCode code="completed"/>            <effectiveTime value="20250110005609"/>            <value xsi:type="PQ" value="473.51705617898375" unit="fL"/>          </observation>        </component>        <component>          <observation classCode="OBS" moodCode="EVN">            <templateId root="2.16.840.1.113883.10.20.22.4.2" extension="2015-08-01"/>            <templateId root="2.16.840.1.113883.10.20.22.4.2"/>            <id root="80e2870f-c321-e7b3-b07d-0100748255d0"/>        <code  code="32623-1" codeSystem="2.16.840.1.113883.6.1" displayName="Platelet mean volume [Entitic volume] in Blood by Automated count">          <originalText><reference value="#reports-desc-1"/></originalText>        </code>            <text>              <reference value="#reports-desc-1"/>            </text>            <statusCode code="completed"/>            <effectiveTime value="20250110005609"/>            <value xsi:type="PQ" value="10.24918959665743" unit="fL"/>          </observation>        </component>      </organizer>    </entry>    <entry typeCode="DRIV">      <organizer classCode="BATTERY" moodCode="EVN">        <templateId root="2.16.840.1.113883.10.20.22.4.1" extension="2015-08-01"/>        <templateId root="2.16.840.1.113883.10.20.22.4.1"/>        <!--Result organizer template -->        <id root="fb7368cd-57ca-c521-f79a-ccdd3ff3c260"/>        <code code="69737-5" codeSystem="2.16.840.1.113883.6.1" codeSystemName="LOINC" displayName="Generalized anxiety disorder 7 item (GAD-7)"/>        <statusCode code="completed"/>        <effectiveTime>          <low value="20250110021152"/>          <high value="20250110021152"/>        </effectiveTime>        <component>          <observation classCode="OBS" moodCode="EVN">            <templateId root="2.16.840.1.113883.10.20.22.4.2" extension="2015-08-01"/>            <templateId root="2.16.840.1.113883.10.20.22.4.2"/>            <id root="3cffd912-5776-c293-410d-9aeaf27d2dcc"/>        <code  code="70274-6" codeSystem="2.16.840.1.113883.6.1" displayName="Generalized anxiety disorder 7 item (GAD-7) total score [Reported.PHQ]">          <originalText><reference value="#reports-desc-2"/></originalText>        </code>            <text>              <reference value="#reports-desc-2"/>            </text>            <statusCode code="completed"/>            <effectiveTime value="20250110021152"/>            <value xsi:type="PQ" value="3" unit="{score}"/>          </observation>        </component>      </organizer>    </entry>  </section></component><component>  <!--Problems-->  <section>    <templateId root="2.16.840.1.113883.10.20.22.2.5.1" extension="2015-08-01"/>    <!--Problems section template-->    <code code="11450-4" codeSystem="2.16.840.1.113883.6.1" codeSystemName="LOINC" displayName="Problem list"/>    <title>Problems</title><text>  <table border="1" width="100%">    <thead>      <tr>        <th>Start</th>        <th>Stop</th>        <th>Description</th>        <th>Code</th>      </tr>    </thead>    <tbody>        <tr>          <td>2021-01-01T01:34:12Z</td>          <td></td>          <td ID="conditions-desc-1">Received higher education (finding)</td>          <td ID="conditions-code-1">http://snomed.info/sct 224299000</td>        </tr>        <tr>          <td>2021-01-01T01:34:12Z</td>          <td></td>          <td ID="conditions-desc-2">Full-time employment (finding)</td>          <td ID="conditions-code-2">http://snomed.info/sct 160903007</td>        </tr>        <tr>          <td>2021-01-01T01:34:12Z</td>          <td></td>          <td ID="conditions-desc-3">Lack of access to transportation (finding)</td>          <td ID="conditions-code-3">http://snomed.info/sct 713458007</td>        </tr>        <tr>          <td>2022-01-07T00:56:09Z</td>          <td></td>          <td ID="conditions-desc-4">Medication review due (situation)</td>          <td ID="conditions-code-4">http://snomed.info/sct 314529007</td>        </tr>        <tr>          <td>2022-01-07T01:38:45Z</td>          <td>2025-01-10T01:49:17Z</td>          <td ID="conditions-desc-5">Social isolation (finding)</td>          <td ID="conditions-code-5">http://snomed.info/sct 422650009</td>        </tr>        <tr>          <td>2022-01-07T01:38:45Z</td>          <td>2025-01-10T01:49:17Z</td>          <td ID="conditions-desc-6">Victim of intimate partner abuse (finding)</td>          <td ID="conditions-code-6">http://snomed.info/sct 706893006</td>        </tr>        <tr>          <td>2025-01-10T01:49:17Z</td>          <td></td>          <td ID="conditions-desc-7">Transport problem (finding)</td>          <td ID="conditions-code-7">http://snomed.info/sct 266934004</td>        </tr>        <tr>          <td>2025-01-10T01:49:17Z</td>          <td></td>          <td ID="conditions-desc-8">Stress (finding)</td>          <td ID="conditions-code-8">http://snomed.info/sct 73595000</td>        </tr>        <tr>          <td>2025-01-17T00:56:09Z</td>          <td>2025-02-18T00:56:09Z</td>          <td ID="conditions-desc-9">Normal pregnancy (finding)</td>          <td ID="conditions-code-9">http://snomed.info/sct 72892002</td>        </tr>    </tbody>  </table></text>    <entry typeCode="DRIV">      <act classCode="ACT" moodCode="EVN">        <templateId root="2.16.840.1.113883.10.20.22.4.3"/>        <templateId root="2.16.840.1.113883.10.20.22.4.3" extension="2015-08-01"/>        <!-- Problem act template -->        <id root="5662bc5d-40aa-aad9-adfd-657d8d7afdca"/>        <code nullFlavor="NA"/>        <statusCode code="active"/>        <effectiveTime>          <low value="20210101013412"/>                  </effectiveTime>        <entryRelationship typeCode="SUBJ" inversionInd="false">          <observation classCode="OBS" moodCode="EVN">            <templateId root="2.16.840.1.113883.10.20.22.4.4"/>            <templateId root="2.16.840.1.113883.10.20.22.4.4" extension="2015-08-01"/>            <!--Problem observation template - NOT episode template-->            <id root="63c57eb0-cef8-a9df-efb7-4a4b7091af3b"/>            <code code="64572001" displayName="Condition" codeSystem="2.16.840.1.113883.6.96" codeSystemName="SNOMED-CT">              <translation code="75323-6" displayName="Condition" codeSystem="2.16.840.1.113883.6.1" codeSystemName="LOINC"/>            </code>            <text>              <reference value="#conditions-desc-1"/>            </text>            <statusCode code="completed"/>            <effectiveTime>              <low value="20210101013412"/>                          </effectiveTime>            <priorityCode code="8319008" codeSystem="2.16.840.1.113883.6.96" displayName="Principal diagnosis" />        <value xsi:type="CD" code="224299000" codeSystem="2.16.840.1.113883.6.96" displayName="Received higher education (finding)">          <originalText><reference value="#conditions-desc-1"/></originalText>        </value>          </observation>        </entryRelationship>      </act>    </entry>    <entry typeCode="DRIV">      <act classCode="ACT" moodCode="EVN">        <templateId root="2.16.840.1.113883.10.20.22.4.3"/>        <templateId root="2.16.840.1.113883.10.20.22.4.3" extension="2015-08-01"/>        <!-- Problem act template -->        <id root="57ede274-220f-c90c-706d-4ff61f9e8acf"/>        <code nullFlavor="NA"/>        <statusCode code="active"/>        <effectiveTime>          <low value="20210101013412"/>                  </effectiveTime>        <entryRelationship typeCode="SUBJ" inversionInd="false">          <observation classCode="OBS" moodCode="EVN">            <templateId root="2.16.840.1.113883.10.20.22.4.4"/>            <templateId root="2.16.840.1.113883.10.20.22.4.4" extension="2015-08-01"/>            <!--Problem observation template - NOT episode template-->            <id root="b1c480aa-3deb-1380-0660-52414e35481b"/>            <code code="64572001" displayName="Condition" codeSystem="2.16.840.1.113883.6.96" codeSystemName="SNOMED-CT">              <translation code="75323-6" displayName="Condition" codeSystem="2.16.840.1.113883.6.1" codeSystemName="LOINC"/>            </code>            <text>              <reference value="#conditions-desc-2"/>            </text>            <statusCode code="completed"/>            <effectiveTime>              <low value="20210101013412"/>                          </effectiveTime>            <priorityCode code="8319008" codeSystem="2.16.840.1.113883.6.96" displayName="Principal diagnosis" />        <value xsi:type="CD" code="160903007" codeSystem="2.16.840.1.113883.6.96" displayName="Full-time employment (finding)">          <originalText><reference value="#conditions-desc-2"/></originalText>        </value>          </observation>        </entryRelationship>      </act>    </entry>    <entry typeCode="DRIV">      <act classCode="ACT" moodCode="EVN">        <templateId root="2.16.840.1.113883.10.20.22.4.3"/>        <templateId root="2.16.840.1.113883.10.20.22.4.3" extension="2015-08-01"/>        <!-- Problem act template -->        <id root="5d29ec95-7784-45c8-ed9b-9f002452fe38"/>        <code nullFlavor="NA"/>        <statusCode code="active"/>        <effectiveTime>          <low value="20210101013412"/>                  </effectiveTime>        <entryRelationship typeCode="SUBJ" inversionInd="false">          <observation classCode="OBS" moodCode="EVN">            <templateId root="2.16.840.1.113883.10.20.22.4.4"/>            <templateId root="2.16.840.1.113883.10.20.22.4.4" extension="2015-08-01"/>            <!--Problem observation template - NOT episode template-->            <id root="28864f81-02e9-7d35-ce94-d0f36b380728"/>            <code code="64572001" displayName="Condition" codeSystem="2.16.840.1.113883.6.96" codeSystemName="SNOMED-CT">              <translation code="75323-6" displayName="Condition" codeSystem="2.16.840.1.113883.6.1" codeSystemName="LOINC"/>            </code>            <text>              <reference value="#conditions-desc-3"/>            </text>            <statusCode code="completed"/>            <effectiveTime>              <low value="20210101013412"/>                          </effectiveTime>            <priorityCode code="8319008" codeSystem="2.16.840.1.113883.6.96" displayName="Principal diagnosis" />        <value xsi:type="CD" code="713458007" codeSystem="2.16.840.1.113883.6.96" displayName="Lack of access to transportation (finding)">          <originalText><reference value="#conditions-desc-3"/></originalText>        </value>          </observation>        </entryRelationship>      </act>    </entry>    <entry typeCode="DRIV">      <act classCode="ACT" moodCode="EVN">        <templateId root="2.16.840.1.113883.10.20.22.4.3"/>        <templateId root="2.16.840.1.113883.10.20.22.4.3" extension="2015-08-01"/>        <!-- Problem act template -->        <id root="d5e8a2dd-22e3-acd6-ddeb-c74933dd090c"/>        <code nullFlavor="NA"/>        <statusCode code="active"/>        <effectiveTime>          <low value="20220107005609"/>                  </effectiveTime>        <entryRelationship typeCode="SUBJ" inversionInd="false">          <observation classCode="OBS" moodCode="EVN">            <templateId root="2.16.840.1.113883.10.20.22.4.4"/>            <templateId root="2.16.840.1.113883.10.20.22.4.4" extension="2015-08-01"/>            <!--Problem observation template - NOT episode template-->            <id root="bbdea4c2-ffc2-74c4-29fe-cb4ccca95546"/>            <code code="64572001" displayName="Condition" codeSystem="2.16.840.1.113883.6.96" codeSystemName="SNOMED-CT">              <translation code="75323-6" displayName="Condition" codeSystem="2.16.840.1.113883.6.1" codeSystemName="LOINC"/>            </code>            <text>              <reference value="#conditions-desc-4"/>            </text>            <statusCode code="completed"/>            <effectiveTime>              <low value="20220107005609"/>                          </effectiveTime>            <priorityCode code="8319008" codeSystem="2.16.840.1.113883.6.96" displayName="Principal diagnosis" />        <value xsi:type="CD" code="314529007" codeSystem="2.16.840.1.113883.6.96" displayName="Medication review due (situation)">          <originalText><reference value="#conditions-desc-4"/></originalText>        </value>          </observation>        </entryRelationship>      </act>    </entry>    <entry typeCode="DRIV">      <act classCode="ACT" moodCode="EVN">        <templateId root="2.16.840.1.113883.10.20.22.4.3"/>        <templateId root="2.16.840.1.113883.10.20.22.4.3" extension="2015-08-01"/>        <!-- Problem act template -->        <id root="9dfacf68-6a56-f31b-2cec-e1e178cf8cab"/>        <code nullFlavor="NA"/>        <statusCode code="completed"/>        <effectiveTime>          <low value="20220107013845"/>          <high value="20250110014917"/>        </effectiveTime>        <entryRelationship typeCode="SUBJ" inversionInd="false">          <observation classCode="OBS" moodCode="EVN">            <templateId root="2.16.840.1.113883.10.20.22.4.4"/>            <templateId root="2.16.840.1.113883.10.20.22.4.4" extension="2015-08-01"/>            <!--Problem observation template - NOT episode template-->            <id root="c83a3b70-1a2a-4b3a-40d0-88a4a9ce71a4"/>            <code code="64572001" displayName="Condition" codeSystem="2.16.840.1.113883.6.96" codeSystemName="SNOMED-CT">              <translation code="75323-6" displayName="Condition" codeSystem="2.16.840.1.113883.6.1" codeSystemName="LOINC"/>            </code>            <text>              <reference value="#conditions-desc-5"/>            </text>            <statusCode code="completed"/>            <effectiveTime>              <low value="20220107013845"/>              <high value="20250110014917"/>            </effectiveTime>            <priorityCode code="8319008" codeSystem="2.16.840.1.113883.6.96" displayName="Principal diagnosis" />        <value xsi:type="CD" code="422650009" codeSystem="2.16.840.1.113883.6.96" displayName="Social isolation (finding)">          <originalText><reference value="#conditions-desc-5"/></originalText>        </value>          </observation>        </entryRelationship>      </act>    </entry>    <entry typeCode="DRIV">      <act classCode="ACT" moodCode="EVN">        <templateId root="2.16.840.1.113883.10.20.22.4.3"/>        <templateId root="2.16.840.1.113883.10.20.22.4.3" extension="2015-08-01"/>        <!-- Problem act template -->        <id root="6f18feac-d2d4-c32a-b714-6d5f36b028e2"/>        <code nullFlavor="NA"/>        <statusCode code="completed"/>        <effectiveTime>          <low value="20220107013845"/>          <high value="20250110014917"/>        </effectiveTime>        <entryRelationship typeCode="SUBJ" inversionInd="false">          <observation classCode="OBS" moodCode="EVN">            <templateId root="2.16.840.1.113883.10.20.22.4.4"/>            <templateId root="2.16.840.1.113883.10.20.22.4.4" extension="2015-08-01"/>            <!--Problem observation template - NOT episode template-->            <id root="d2f92835-b561-5b0f-91c4-c80c6d929e88"/>            <code code="64572001" displayName="Condition" codeSystem="2.16.840.1.113883.6.96" codeSystemName="SNOMED-CT">              <translation code="75323-6" displayName="Condition" codeSystem="2.16.840.1.113883.6.1" codeSystemName="LOINC"/>            </code>            <text>              <reference value="#conditions-desc-6"/>            </text>            <statusCode code="completed"/>            <effectiveTime>              <low value="20220107013845"/>              <high value="20250110014917"/>            </effectiveTime>            <priorityCode code="8319008" codeSystem="2.16.840.1.113883.6.96" displayName="Principal diagnosis" />        <value xsi:type="CD" code="706893006" codeSystem="2.16.840.1.113883.6.96" displayName="Victim of intimate partner abuse (finding)">          <originalText><reference value="#conditions-desc-6"/></originalText>        </value>          </observation>        </entryRelationship>      </act>    </entry>    <entry typeCode="DRIV">      <act classCode="ACT" moodCode="EVN">        <templateId root="2.16.840.1.113883.10.20.22.4.3"/>        <templateId root="2.16.840.1.113883.10.20.22.4.3" extension="2015-08-01"/>        <!-- Problem act template -->        <id root="e675ccaa-763e-df3b-7041-5a9706d1dd94"/>        <code nullFlavor="NA"/>        <statusCode code="active"/>        <effectiveTime>          <low value="20250110014917"/>                  </effectiveTime>        <entryRelationship typeCode="SUBJ" inversionInd="false">          <observation classCode="OBS" moodCode="EVN">            <templateId root="2.16.840.1.113883.10.20.22.4.4"/>            <templateId root="2.16.840.1.113883.10.20.22.4.4" extension="2015-08-01"/>            <!--Problem observation template - NOT episode template-->            <id root="2c1a00e2-4476-0c88-4c5c-76e73d46d651"/>            <code code="64572001" displayName="Condition" codeSystem="2.16.840.1.113883.6.96" codeSystemName="SNOMED-CT">              <translation code="75323-6" displayName="Condition" codeSystem="2.16.840.1.113883.6.1" codeSystemName="LOINC"/>            </code>            <text>              <reference value="#conditions-desc-7"/>            </text>            <statusCode code="completed"/>            <effectiveTime>              <low value="20250110014917"/>                          </effectiveTime>            <priorityCode code="8319008" codeSystem="2.16.840.1.113883.6.96" displayName="Principal diagnosis" />        <value xsi:type="CD" code="266934004" codeSystem="2.16.840.1.113883.6.96" displayName="Transport problem (finding)">          <originalText><reference value="#conditions-desc-7"/></originalText>        </value>          </observation>        </entryRelationship>      </act>    </entry>    <entry typeCode="DRIV">      <act classCode="ACT" moodCode="EVN">        <templateId root="2.16.840.1.113883.10.20.22.4.3"/>        <templateId root="2.16.840.1.113883.10.20.22.4.3" extension="2015-08-01"/>        <!-- Problem act template -->        <id root="f2a588c6-1d7b-9871-5917-d0de4bac5e86"/>        <code nullFlavor="NA"/>        <statusCode code="active"/>        <effectiveTime>          <low value="20250110014917"/>                  </effectiveTime>        <entryRelationship typeCode="SUBJ" inversionInd="false">          <observation classCode="OBS" moodCode="EVN">            <templateId root="2.16.840.1.113883.10.20.22.4.4"/>            <templateId root="2.16.840.1.113883.10.20.22.4.4" extension="2015-08-01"/>            <!--Problem observation template - NOT episode template-->            <id root="e22b8712-bd78-3c5c-6328-bcbd08394cba"/>            <code code="64572001" displayName="Condition" codeSystem="2.16.840.1.113883.6.96" codeSystemName="SNOMED-CT">              <translation code="75323-6" displayName="Condition" codeSystem="2.16.840.1.113883.6.1" codeSystemName="LOINC"/>            </code>            <text>              <reference value="#conditions-desc-8"/>            </text>            <statusCode code="completed"/>            <effectiveTime>              <low value="20250110014917"/>                          </effectiveTime>            <priorityCode code="8319008" codeSystem="2.16.840.1.113883.6.96" displayName="Principal diagnosis" />        <value xsi:type="CD" code="73595000" codeSystem="2.16.840.1.113883.6.96" displayName="Stress (finding)">          <originalText><reference value="#conditions-desc-8"/></originalText>        </value>          </observation>        </entryRelationship>      </act>    </entry>    <entry typeCode="DRIV">      <act classCode="ACT" moodCode="EVN">        <templateId root="2.16.840.1.113883.10.20.22.4.3"/>        <templateId root="2.16.840.1.113883.10.20.22.4.3" extension="2015-08-01"/>        <!-- Problem act template -->        <id root="dc2f9c79-5c4f-a5a7-73f7-866a57194d87"/>        <code nullFlavor="NA"/>        <statusCode code="completed"/>        <effectiveTime>          <low value="20250117005609"/>          <high value="20250218005609"/>        </effectiveTime>        <entryRelationship typeCode="SUBJ" inversionInd="false">          <observation classCode="OBS" moodCode="EVN">            <templateId root="2.16.840.1.113883.10.20.22.4.4"/>            <templateId root="2.16.840.1.113883.10.20.22.4.4" extension="2015-08-01"/>            <!--Problem observation template - NOT episode template-->            <id root="a6a1ca30-3329-e89a-d189-70509d6d405b"/>            <code code="64572001" displayName="Condition" codeSystem="2.16.840.1.113883.6.96" codeSystemName="SNOMED-CT">              <translation code="75323-6" displayName="Condition" codeSystem="2.16.840.1.113883.6.1" codeSystemName="LOINC"/>            </code>            <text>              <reference value="#conditions-desc-9"/>            </text>            <statusCode code="completed"/>            <effectiveTime>              <low value="20250117005609"/>              <high value="20250218005609"/>            </effectiveTime>            <priorityCode code="8319008" codeSystem="2.16.840.1.113883.6.96" displayName="Principal diagnosis" />        <value xsi:type="CD" code="72892002" codeSystem="2.16.840.1.113883.6.96" displayName="Normal pregnancy (finding)">          <originalText><reference value="#conditions-desc-9"/></originalText>        </value>          </observation>        </entryRelationship>      </act>    </entry>  </section></component><component>  <!--Surgeries-->  <section>    <templateId root="2.16.840.1.113883.10.20.22.2.7.1" extension="2014-06-09"/>    <!--Surgeries section template-->    <code code="47519-4" codeSystem="2.16.840.1.113883.6.1" codeSystemName="LOINC" displayName="List of surgeries"/>    <title>Surgeries</title><text>  <table border="1" width="100%">    <thead>      <tr>        <th>Start</th>        <th>Stop</th>        <th>Description</th>        <th>Code</th>      </tr>    </thead>    <tbody>        <tr>          <td>2025-01-10T00:56:09Z</td>          <td>2025-01-10T01:49:17Z</td>          <td ID="procedures-desc-1">Assessment of health and social care needs (procedure)</td>          <td ID="procedures-code-1">http://snomed.info/sct 710824005</td>        </tr>        <tr>          <td>2025-01-10T01:49:17Z</td>          <td>2025-01-10T02:11:52Z</td>          <td ID="procedures-desc-2">Assessment of anxiety (procedure)</td>          <td ID="procedures-code-2">http://snomed.info/sct 710841007</td>        </tr>        <tr>          <td>2025-01-10T02:11:52Z</td>          <td>2025-01-10T02:17:49Z</td>          <td ID="procedures-desc-3">Patient referral for dental care (procedure)</td>          <td ID="procedures-code-3">http://snomed.info/sct 103697008</td>        </tr>        <tr>          <td>2025-01-17T00:56:09Z</td>          <td>2025-01-17T01:11:09Z</td>          <td ID="procedures-desc-4">Standard pregnancy test (procedure)</td>          <td ID="procedures-code-4">http://snomed.info/sct 252160004</td>        </tr>        <tr>          <td>2025-01-17T00:56:09Z</td>          <td>2025-01-17T01:11:09Z</td>          <td ID="procedures-desc-5">Ultrasound scan for fetal viability (procedure)</td>          <td ID="procedures-code-5">http://snomed.info/sct 169230002</td>        </tr>        <tr>          <td>2025-01-24T00:56:09Z</td>          <td>2025-01-24T01:24:45Z</td>          <td ID="procedures-desc-6">Dental consultation and report (procedure)</td>          <td ID="procedures-code-6">http://snomed.info/sct 34043003</td>        </tr>        <tr>          <td>2025-01-24T01:24:45Z</td>          <td>2025-01-24T02:01:38Z</td>          <td ID="procedures-desc-7">Dental care (regime/therapy)</td>          <td ID="procedures-code-7">http://snomed.info/sct 225362009</td>        </tr>        <tr>          <td>2025-01-24T02:01:38Z</td>          <td>2025-01-24T02:26:14Z</td>          <td ID="procedures-desc-8">Removal of supragingival plaque and calculus from all teeth using dental instrument (procedure)</td>          <td ID="procedures-code-8">http://snomed.info/sct 1260009003</td>        </tr>        <tr>          <td>2025-01-24T02:26:14Z</td>          <td>2025-01-24T02:51:10Z</td>          <td ID="procedures-desc-9">Removal of subgingival plaque and calculus from all teeth using dental instrument (procedure)</td>          <td ID="procedures-code-9">http://snomed.info/sct 1260010008</td>        </tr>        <tr>          <td>2025-01-24T02:51:10Z</td>          <td>2025-01-24T03:21:10Z</td>          <td ID="procedures-desc-10">Dental plain X-ray bitewing (procedure)</td>          <td ID="procedures-code-10">http://snomed.info/sct 241046008</td>        </tr>        <tr>          <td>2025-01-24T02:51:10Z</td>          <td>2025-01-24T03:42:38Z</td>          <td ID="procedures-desc-11">Examination of gingivae (procedure)</td>          <td ID="procedures-code-11">http://snomed.info/sct 274788003</td>        </tr>        <tr>          <td>2025-01-24T03:42:38Z</td>          <td>2025-01-24T03:52:10Z</td>          <td ID="procedures-desc-12">Oral health education (procedure)</td>          <td ID="procedures-code-12">http://snomed.info/sct 243085009</td>        </tr>        <tr>          <td>2025-02-03T00:56:09Z</td>          <td>2025-02-03T01:11:09Z</td>          <td ID="procedures-desc-13">Counseling for termination of pregnancy (procedure)</td>          <td ID="procedures-code-13">http://snomed.info/sct 10383002</td>        </tr>        <tr>          <td>2025-02-03T00:56:09Z</td>          <td>2025-02-03T01:11:09Z</td>          <td ID="procedures-desc-14">Induced termination of pregnancy (procedure)</td>          <td ID="procedures-code-14">http://snomed.info/sct 714812005</td>        </tr>        <tr>          <td>2025-02-18T00:56:09Z</td>          <td>2025-02-18T01:11:09Z</td>          <td ID="procedures-desc-15">Pregnancy termination care (regime/therapy)</td>          <td ID="procedures-code-15">http://snomed.info/sct 386394001</td>        </tr>        <tr>          <td>2025-02-18T00:56:09Z</td>          <td>2025-02-18T01:11:09Z</td>          <td ID="procedures-desc-16">Physical examination procedure (procedure)</td>          <td ID="procedures-code-16">http://snomed.info/sct 5880005</td>        </tr>        <tr>          <td>2025-02-18T00:56:09Z</td>          <td>2025-02-18T01:11:09Z</td>          <td ID="procedures-desc-17">Depression screening (procedure)</td>          <td ID="procedures-code-17">http://snomed.info/sct 171207006</td>        </tr>    </tbody>  </table></text>    <entry typeCode="DRIV">      <procedure classCode="PROC" moodCode="EVN">        <templateId root="2.16.840.1.113883.10.20.22.4.14"/>        <!-- Procedure activity template -->        <id root="7b73ba4f-7545-f0cb-1413-8d8c6fe708df"/>        <code  code="710824005" codeSystem="2.16.840.1.113883.6.96" displayName="Assessment of health and social care needs (procedure)">          <originalText><reference value="#procedures-desc-1"/></originalText>        </code>        <text>          <reference value="#procedures-desc-1"/>        </text>        <statusCode code="completed"/>        <effectiveTime value="20250110005609"/>      </procedure>    </entry>    <entry typeCode="DRIV">      <procedure classCode="PROC" moodCode="EVN">        <templateId root="2.16.840.1.113883.10.20.22.4.14"/>        <!-- Procedure activity template -->        <id root="83d622ce-578a-a88e-addd-9e0e4820c993"/>        <code  code="710841007" codeSystem="2.16.840.1.113883.6.96" displayName="Assessment of anxiety (procedure)">          <originalText><reference value="#procedures-desc-2"/></originalText>        </code>        <text>          <reference value="#procedures-desc-2"/>        </text>        <statusCode code="completed"/>        <effectiveTime value="20250110014917"/>      </procedure>    </entry>    <entry typeCode="DRIV">      <procedure classCode="PROC" moodCode="EVN">        <templateId root="2.16.840.1.113883.10.20.22.4.14"/>        <!-- Procedure activity template -->        <id root="59493e6c-aab0-6775-843c-c2e0d20c716d"/>        <code  code="103697008" codeSystem="2.16.840.1.113883.6.96" displayName="Patient referral for dental care (procedure)">          <originalText><reference value="#procedures-desc-3"/></originalText>        </code>        <text>          <reference value="#procedures-desc-3"/>        </text>        <statusCode code="completed"/>        <effectiveTime value="20250110021152"/>      </procedure>    </entry>    <entry typeCode="DRIV">      <procedure classCode="PROC" moodCode="EVN">        <templateId root="2.16.840.1.113883.10.20.22.4.14"/>        <!-- Procedure activity template -->        <id root="22ae1d65-6f43-764b-ca8f-6d35a56e5776"/>        <code  code="252160004" codeSystem="2.16.840.1.113883.6.96" displayName="Standard pregnancy test (procedure)">          <originalText><reference value="#procedures-desc-4"/></originalText>        </code>        <text>          <reference value="#procedures-desc-4"/>        </text>        <statusCode code="completed"/>        <effectiveTime value="20250117005609"/>      </procedure>    </entry>    <entry typeCode="DRIV">      <procedure classCode="PROC" moodCode="EVN">        <templateId root="2.16.840.1.113883.10.20.22.4.14"/>        <!-- Procedure activity template -->        <id root="55bc79c1-a3f2-6001-1ef4-854f245ebc88"/>        <code  code="169230002" codeSystem="2.16.840.1.113883.6.96" displayName="Ultrasound scan for fetal viability (procedure)">          <originalText><reference value="#procedures-desc-5"/></originalText>        </code>        <text>          <reference value="#procedures-desc-5"/>        </text>        <statusCode code="completed"/>        <effectiveTime value="20250117005609"/>      </procedure>    </entry>    <entry typeCode="DRIV">      <procedure classCode="PROC" moodCode="EVN">        <templateId root="2.16.840.1.113883.10.20.22.4.14"/>        <!-- Procedure activity template -->        <id root="2bd6cc8d-1dc8-d0e7-4b1e-865ce40702ad"/>        <code  code="34043003" codeSystem="2.16.840.1.113883.6.96" displayName="Dental consultation and report (procedure)">          <originalText><reference value="#procedures-desc-6"/></originalText>        </code>        <text>          <reference value="#procedures-desc-6"/>        </text>        <statusCode code="completed"/>        <effectiveTime value="20250124005609"/>      </procedure>    </entry>    <entry typeCode="DRIV">      <procedure classCode="PROC" moodCode="EVN">        <templateId root="2.16.840.1.113883.10.20.22.4.14"/>        <!-- Procedure activity template -->        <id root="7c0c74ab-251d-d434-7c3b-c4ae77ef57ac"/>        <code  code="225362009" codeSystem="2.16.840.1.113883.6.96" displayName="Dental care (regime/therapy)">          <originalText><reference value="#procedures-desc-7"/></originalText>        </code>        <text>          <reference value="#procedures-desc-7"/>        </text>        <statusCode code="completed"/>        <effectiveTime value="20250124012445"/>      </procedure>    </entry>    <entry typeCode="DRIV">      <procedure classCode="PROC" moodCode="EVN">        <templateId root="2.16.840.1.113883.10.20.22.4.14"/>        <!-- Procedure activity template -->        <id root="eb23e2f9-8a89-b809-9097-1b42ca2cadf9"/>        <code  code="1260009003" codeSystem="2.16.840.1.113883.6.96" displayName="Removal of supragingival plaque and calculus from all teeth using dental instrument (procedure)">          <originalText><reference value="#procedures-desc-8"/></originalText>        </code>        <text>          <reference value="#procedures-desc-8"/>        </text>        <statusCode code="completed"/>        <effectiveTime value="20250124020138"/>      </procedure>    </entry>    <entry typeCode="DRIV">      <procedure classCode="PROC" moodCode="EVN">        <templateId root="2.16.840.1.113883.10.20.22.4.14"/>        <!-- Procedure activity template -->        <id root="1d8971af-889e-06cb-3238-d80e3c89a730"/>        <code  code="1260010008" codeSystem="2.16.840.1.113883.6.96" displayName="Removal of subgingival plaque and calculus from all teeth using dental instrument (procedure)">          <originalText><reference value="#procedures-desc-9"/></originalText>        </code>        <text>          <reference value="#procedures-desc-9"/>        </text>        <statusCode code="completed"/>        <effectiveTime value="20250124022614"/>      </procedure>    </entry>    <entry typeCode="DRIV">      <procedure classCode="PROC" moodCode="EVN">        <templateId root="2.16.840.1.113883.10.20.22.4.14"/>        <!-- Procedure activity template -->        <id root="a4d3f1d6-b9b9-4551-99dd-6e9c3af881d7"/>        <code  code="241046008" codeSystem="2.16.840.1.113883.6.96" displayName="Dental plain X-ray bitewing (procedure)">          <originalText><reference value="#procedures-desc-10"/></originalText>        </code>        <text>          <reference value="#procedures-desc-10"/>        </text>        <statusCode code="completed"/>        <effectiveTime value="20250124025110"/>      </procedure>    </entry>    <entry typeCode="DRIV">      <procedure classCode="PROC" moodCode="EVN">        <templateId root="2.16.840.1.113883.10.20.22.4.14"/>        <!-- Procedure activity template -->        <id root="ac55f7ae-746e-a3ae-5107-719c92df6d08"/>        <code  code="274788003" codeSystem="2.16.840.1.113883.6.96" displayName="Examination of gingivae (procedure)">          <originalText><reference value="#procedures-desc-11"/></originalText>        </code>        <text>          <reference value="#procedures-desc-11"/>        </text>        <statusCode code="completed"/>        <effectiveTime value="20250124025110"/>      </procedure>    </entry>    <entry typeCode="DRIV">      <procedure classCode="PROC" moodCode="EVN">        <templateId root="2.16.840.1.113883.10.20.22.4.14"/>        <!-- Procedure activity template -->        <id root="11fd6164-53ce-80cc-0037-d15b36e17534"/>        <code  code="243085009" codeSystem="2.16.840.1.113883.6.96" displayName="Oral health education (procedure)">          <originalText><reference value="#procedures-desc-12"/></originalText>        </code>        <text>          <reference value="#procedures-desc-12"/>        </text>        <statusCode code="completed"/>        <effectiveTime value="20250124034238"/>      </procedure>    </entry>    <entry typeCode="DRIV">      <procedure classCode="PROC" moodCode="EVN">        <templateId root="2.16.840.1.113883.10.20.22.4.14"/>        <!-- Procedure activity template -->        <id root="9da0cd56-5cdf-6f21-b400-91d3ecc1a88f"/>        <code  code="10383002" codeSystem="2.16.840.1.113883.6.96" displayName="Counseling for termination of pregnancy (procedure)">          <originalText><reference value="#procedures-desc-13"/></originalText>        </code>        <text>          <reference value="#procedures-desc-13"/>        </text>        <statusCode code="completed"/>        <effectiveTime value="20250203005609"/>      </procedure>    </entry>    <entry typeCode="DRIV">      <procedure classCode="PROC" moodCode="EVN">        <templateId root="2.16.840.1.113883.10.20.22.4.14"/>        <!-- Procedure activity template -->        <id root="1c3bd613-1962-c91a-7aa2-9a1d9889bc86"/>        <code  code="714812005" codeSystem="2.16.840.1.113883.6.96" displayName="Induced termination of pregnancy (procedure)">          <originalText><reference value="#procedures-desc-14"/></originalText>        </code>        <text>          <reference value="#procedures-desc-14"/>        </text>        <statusCode code="completed"/>        <effectiveTime value="20250203005609"/>      </procedure>    </entry>    <entry typeCode="DRIV">      <procedure classCode="PROC" moodCode="EVN">        <templateId root="2.16.840.1.113883.10.20.22.4.14"/>        <!-- Procedure activity template -->        <id root="57b76cd9-89ff-4312-98bf-af548deff77e"/>        <code  code="386394001" codeSystem="2.16.840.1.113883.6.96" displayName="Pregnancy termination care (regime/therapy)">          <originalText><reference value="#procedures-desc-15"/></originalText>        </code>        <text>          <reference value="#procedures-desc-15"/>        </text>        <statusCode code="completed"/>        <effectiveTime value="20250218005609"/>      </procedure>    </entry>    <entry typeCode="DRIV">      <procedure classCode="PROC" moodCode="EVN">        <templateId root="2.16.840.1.113883.10.20.22.4.14"/>        <!-- Procedure activity template -->        <id root="36b46a73-bb32-8901-c1f9-0f3903b1a6c3"/>        <code  code="5880005" codeSystem="2.16.840.1.113883.6.96" displayName="Physical examination procedure (procedure)">          <originalText><reference value="#procedures-desc-16"/></originalText>        </code>        <text>          <reference value="#procedures-desc-16"/>        </text>        <statusCode code="completed"/>        <effectiveTime value="20250218005609"/>      </procedure>    </entry>    <entry typeCode="DRIV">      <procedure classCode="PROC" moodCode="EVN">        <templateId root="2.16.840.1.113883.10.20.22.4.14"/>        <!-- Procedure activity template -->        <id root="a5b2d120-398e-a559-8327-bb084a64729a"/>        <code  code="171207006" codeSystem="2.16.840.1.113883.6.96" displayName="Depression screening (procedure)">          <originalText><reference value="#procedures-desc-17"/></originalText>        </code>        <text>          <reference value="#procedures-desc-17"/>        </text>        <statusCode code="completed"/>        <effectiveTime value="20250218005609"/>      </procedure>    </entry>  </section></component><component>  <!--Encounters-->  <section>    <templateId root="2.16.840.1.113883.10.20.22.2.22" extension="2015-08-01"/> <!-- CCDA Template id -->    <!--Encounters section template-->    <code code="46240-8" codeSystem="2.16.840.1.113883.6.1" codeSystemName="LOINC" displayName="History of encounters"/>    <title>Encounters</title><text>  <table border="1" width="100%">    <thead>      <tr>        <th>Start</th>        <th>Stop</th>        <th>Description</th>        <th>Code</th>      </tr>    </thead>    <tbody>        <tr>          <td>2006-09-26T00:56:09Z</td>          <td>2006-09-26T01:11:09Z</td>          <td ID="encounters-desc-1">Encounter for symptom (procedure)</td>          <td ID="encounters-code-1">http://snomed.info/sct 185345009</td>        </tr>        <tr>          <td>2006-10-02T19:56:09Z</td>          <td>2006-10-02T20:26:20Z</td>          <td ID="encounters-desc-2">Encounter for problem (procedure)</td>          <td ID="encounters-code-2">http://snomed.info/sct 185347001</td>        </tr>        <tr>          <td>2021-01-01T00:56:09Z</td>          <td>2021-01-01T01:34:12Z</td>          <td ID="encounters-desc-3">General examination of patient (procedure)</td>          <td ID="encounters-code-3">http://snomed.info/sct 162673000</td>        </tr>        <tr>          <td>2021-10-12T00:56:09Z</td>          <td>2021-10-12T01:11:09Z</td>          <td ID="encounters-desc-4">Consultation for treatment (procedure)</td>          <td ID="encounters-code-4">http://snomed.info/sct 698314001</td>        </tr>        <tr>          <td>2022-01-07T00:56:09Z</td>          <td>2022-01-07T01:38:45Z</td>          <td ID="encounters-desc-5">General examination of patient (procedure)</td>          <td ID="encounters-code-5">http://snomed.info/sct 162673000</td>        </tr>        <tr>          <td>2022-10-07T00:56:09Z</td>          <td>2022-10-07T01:11:09Z</td>          <td ID="encounters-desc-6">Consultation for treatment (procedure)</td>          <td ID="encounters-code-6">http://snomed.info/sct 698314001</td>        </tr>        <tr>          <td>2025-01-10T00:56:09Z</td>          <td>2025-01-10T01:49:17Z</td>          <td ID="encounters-desc-7">General examination of patient (procedure)</td>          <td ID="encounters-code-7">http://snomed.info/sct 162673000</td>        </tr>        <tr>          <td>2025-01-17T00:56:09Z</td>          <td>2025-01-17T01:11:09Z</td>          <td ID="encounters-desc-8">Prenatal initial visit (regime/therapy)</td>          <td ID="encounters-code-8">http://snomed.info/sct 424441002</td>        </tr>        <tr>          <td>2025-01-24T00:56:09Z</td>          <td>2025-01-24T03:52:10Z</td>          <td ID="encounters-desc-9">Encounter for check up (procedure)</td>          <td ID="encounters-code-9">http://snomed.info/sct 185349003</td>        </tr>        <tr>          <td>2025-02-03T00:56:09Z</td>          <td>2025-02-03T01:11:09Z</td>          <td ID="encounters-desc-10">Patient-initiated encounter (procedure)</td>          <td ID="encounters-code-10">http://snomed.info/sct 270427003</td>        </tr>        <tr>          <td>2025-02-18T00:56:09Z</td>          <td>2025-02-18T01:11:09Z</td>          <td ID="encounters-desc-11">Prenatal visit (regime/therapy)</td>          <td ID="encounters-code-11">http://snomed.info/sct 424619006</td>        </tr>    </tbody>  </table></text>    <entry typeCode="DRIV">      <encounter classCode="ENC" moodCode="EVN">		    <templateId root="2.16.840.1.113883.10.20.22.4.49"/>        <!-- Encounter activity template -->        <id root="c56e7ce9-3b97-c7ef-b8c5-85f2b93ce7c1"/>        <code  code="185345009" codeSystem="2.16.840.1.113883.6.96" displayName="Encounter for symptom (procedure)">          <originalText><reference value="#encounters-desc-1"/></originalText>        </code>        <text>          <reference value="#encounters-desc-1"/>        </text>        <effectiveTime>          <low value="20060926005609"/>          <high value="20060926011109"/>        </effectiveTime>      </encounter>    </entry>    <entry typeCode="DRIV">      <encounter classCode="ENC" moodCode="EVN">		    <templateId root="2.16.840.1.113883.10.20.22.4.49"/>        <!-- Encounter activity template -->        <id root="d13eff57-8e65-bc7b-c551-a617e3521a16"/>        <code  code="185347001" codeSystem="2.16.840.1.113883.6.96" displayName="Encounter for problem (procedure)">          <originalText><reference value="#encounters-desc-2"/></originalText>        </code>        <text>          <reference value="#encounters-desc-2"/>        </text>        <effectiveTime>          <low value="20061002195609"/>          <high value="20061002202620"/>        </effectiveTime>      </encounter>    </entry>    <entry typeCode="DRIV">      <encounter classCode="ENC" moodCode="EVN">		    <templateId root="2.16.840.1.113883.10.20.22.4.49"/>        <!-- Encounter activity template -->        <id root="51afc92e-ae72-cf94-1f7f-b2f87e585daf"/>        <code  code="162673000" codeSystem="2.16.840.1.113883.6.96" displayName="General examination of patient (procedure)">          <originalText><reference value="#encounters-desc-3"/></originalText>        </code>        <text>          <reference value="#encounters-desc-3"/>        </text>        <effectiveTime>          <low value="20210101005609"/>          <high value="20210101013412"/>        </effectiveTime>      </encounter>    </entry>    <entry typeCode="DRIV">      <encounter classCode="ENC" moodCode="EVN">		    <templateId root="2.16.840.1.113883.10.20.22.4.49"/>        <!-- Encounter activity template -->        <id root="d57677a8-f49c-5f48-406b-8a50896a754e"/>        <code  code="698314001" codeSystem="2.16.840.1.113883.6.96" displayName="Consultation for treatment (procedure)">          <originalText><reference value="#encounters-desc-4"/></originalText>        </code>        <text>          <reference value="#encounters-desc-4"/>        </text>        <effectiveTime>          <low value="20211012005609"/>          <high value="20211012011109"/>        </effectiveTime>      </encounter>    </entry>    <entry typeCode="DRIV">      <encounter classCode="ENC" moodCode="EVN">		    <templateId root="2.16.840.1.113883.10.20.22.4.49"/>        <!-- Encounter activity template -->        <id root="307fed5c-cae7-61d0-fda0-901a1b31b9cb"/>        <code  code="162673000" codeSystem="2.16.840.1.113883.6.96" displayName="General examination of patient (procedure)">          <originalText><reference value="#encounters-desc-5"/></originalText>        </code>        <text>          <reference value="#encounters-desc-5"/>        </text>        <effectiveTime>          <low value="20220107005609"/>          <high value="20220107013845"/>        </effectiveTime>      </encounter>    </entry>    <entry typeCode="DRIV">      <encounter classCode="ENC" moodCode="EVN">		    <templateId root="2.16.840.1.113883.10.20.22.4.49"/>        <!-- Encounter activity template -->        <id root="2a017c35-5359-5b8f-6ef9-9adf8a4303c3"/>        <code  code="698314001" codeSystem="2.16.840.1.113883.6.96" displayName="Consultation for treatment (procedure)">          <originalText><reference value="#encounters-desc-6"/></originalText>        </code>        <text>          <reference value="#encounters-desc-6"/>        </text>        <effectiveTime>          <low value="20221007005609"/>          <high value="20221007011109"/>        </effectiveTime>      </encounter>    </entry>    <entry typeCode="DRIV">      <encounter classCode="ENC" moodCode="EVN">		    <templateId root="2.16.840.1.113883.10.20.22.4.49"/>        <!-- Encounter activity template -->        <id root="ca30a7a5-6ecc-89c3-a05a-160b7cd85078"/>        <code  code="162673000" codeSystem="2.16.840.1.113883.6.96" displayName="General examination of patient (procedure)">          <originalText><reference value="#encounters-desc-7"/></originalText>        </code>        <text>          <reference value="#encounters-desc-7"/>        </text>        <effectiveTime>          <low value="20250110005609"/>          <high value="20250110014917"/>        </effectiveTime>      </encounter>    </entry>    <entry typeCode="DRIV">      <encounter classCode="ENC" moodCode="EVN">		    <templateId root="2.16.840.1.113883.10.20.22.4.49"/>        <!-- Encounter activity template -->        <id root="8e47ffa5-6b41-33d5-8fa3-a1a4c077af1f"/>        <code  code="424441002" codeSystem="2.16.840.1.113883.6.96" displayName="Prenatal initial visit (regime/therapy)">          <originalText><reference value="#encounters-desc-8"/></originalText>        </code>        <text>          <reference value="#encounters-desc-8"/>        </text>        <effectiveTime>          <low value="20250117005609"/>          <high value="20250117011109"/>        </effectiveTime>      </encounter>    </entry>    <entry typeCode="DRIV">      <encounter classCode="ENC" moodCode="EVN">		    <templateId root="2.16.840.1.113883.10.20.22.4.49"/>        <!-- Encounter activity template -->        <id root="d6f4a594-198f-dd77-6827-5573f12c1ef2"/>        <code  code="185349003" codeSystem="2.16.840.1.113883.6.96" displayName="Encounter for check up (procedure)">          <originalText><reference value="#encounters-desc-9"/></originalText>        </code>        <text>          <reference value="#encounters-desc-9"/>        </text>        <effectiveTime>          <low value="20250124005609"/>          <high value="20250124035210"/>        </effectiveTime>      </encounter>    </entry>    <entry typeCode="DRIV">      <encounter classCode="ENC" moodCode="EVN">		    <templateId root="2.16.840.1.113883.10.20.22.4.49"/>        <!-- Encounter activity template -->        <id root="80732e19-c8a7-76da-cf7a-ac36c6a3ea3a"/>        <code  code="270427003" codeSystem="2.16.840.1.113883.6.96" displayName="Patient-initiated encounter (procedure)">          <originalText><reference value="#encounters-desc-10"/></originalText>        </code>        <text>          <reference value="#encounters-desc-10"/>        </text>        <effectiveTime>          <low value="20250203005609"/>          <high value="20250203011109"/>        </effectiveTime>      </encounter>    </entry>    <entry typeCode="DRIV">      <encounter classCode="ENC" moodCode="EVN">		    <templateId root="2.16.840.1.113883.10.20.22.4.49"/>        <!-- Encounter activity template -->        <id root="c03db4b1-8bef-4e15-7043-ad96a7ca0363"/>        <code  code="424619006" codeSystem="2.16.840.1.113883.6.96" displayName="Prenatal visit (regime/therapy)">          <originalText><reference value="#encounters-desc-11"/></originalText>        </code>        <text>          <reference value="#encounters-desc-11"/>        </text>        <effectiveTime>          <low value="20250218005609"/>          <high value="20250218011109"/>        </effectiveTime>      </encounter>    </entry>  </section></component><component>  <!--Vital Signs-->  <section>    <templateId root="2.16.840.1.113883.10.20.22.2.4.1" extension="2015-08-01"/>    <!--Vital Signs section template-->    <code code="8716-3" codeSystem="2.16.840.1.113883.6.1" codeSystemName="LOINC" displayName="Vital signs"/>    <title>Vital Signs</title><text>  <table border="1" width="100%">    <thead>      <tr>        <th>Start</th>        <th>Stop</th>        <th>Description</th>        <th>Code</th>        <th>Value</th>      </tr>    </thead>    <tbody>        <tr>          <td>2025-01-10T00:56:09Z</td>          <td></td>          <td ID="observations-desc-1">Body Height</td>          <td ID="observations-code-1">http://loinc.org 8302-2</td>          <td>169.8 cm</td>        </tr>        <tr>          <td>2025-01-10T00:56:09Z</td>          <td></td>          <td ID="observations-desc-2">Pain severity - 0-10 verbal numeric rating [Score] - Reported</td>          <td ID="observations-code-2">http://loinc.org 72514-3</td>          <td>1 {score}</td>        </tr>        <tr>          <td>2025-01-10T00:56:09Z</td>          <td></td>          <td ID="observations-desc-3">Body Weight</td>          <td ID="observations-code-3">http://loinc.org 29463-7</td>          <td>65.8 kg</td>        </tr>        <tr>          <td>2025-01-10T00:56:09Z</td>          <td></td>          <td ID="observations-desc-4">Body mass index (BMI) [Ratio]</td>          <td ID="observations-code-4">http://loinc.org 39156-5</td>          <td>22.82 kg/m2</td>        </tr>        <tr>          <td>2025-01-10T00:56:09Z</td>          <td></td>          <td ID="observations-desc-5">Heart rate</td>          <td ID="observations-code-5">http://loinc.org 8867-4</td>          <td>77 /min</td>        </tr>        <tr>          <td>2025-01-10T00:56:09Z</td>          <td></td>          <td ID="observations-desc-6">Respiratory rate</td>          <td ID="observations-code-6">http://loinc.org 9279-1</td>          <td>14 /min</td>        </tr>    </tbody>  </table></text>    <entry typeCode="DRIV">      <organizer classCode="CLUSTER" moodCode="EVN">        <templateId root="2.16.840.1.113883.10.20.22.4.26"/>        <templateId root="2.16.840.1.113883.10.20.22.4.26" extension="2015-08-01"/>        <!-- Vital signs organizer template -->        <id root="d106f49b-4d13-47c9-5635-49f2b23fe075"/>        <code code="46680005" codeSystem="2.16.840.1.113883.6.96" displayName="Vital signs" codeSystemName="SNOMED CT">          <translation code="74728-7" displayName="Vital signs, weight, height, head circumference, oximetry, BMI, and BSA panel" codeSystem="2.16.840.1.113883.6.1" codeSystemName="LOINC" />        </code>        <statusCode code="completed"/>        <effectiveTime value="20250801005609"/>        <component>          <observation classCode="OBS" moodCode="EVN">            <templateId root="2.16.840.1.113883.10.20.22.4.27"/>            <templateId root="2.16.840.1.113883.10.20.22.4.27" extension="2014-06-09"/>            <!-- Result observation template -->            <id root="a380b129-af21-7e7c-42aa-55b68b49e2d5"/>        <code  code="8302-2" codeSystem="2.16.840.1.113883.6.1" displayName="Body Height">          <originalText><reference value="#observations-desc-1"/></originalText>        </code>            <text>              <reference value="#observations-desc-1"/>            </text>            <statusCode code="completed"/>            <effectiveTime value="20250110005609"/>            <value xsi:type="PQ" value="169.8" unit="cm"/>          </observation>        </component>        <component>          <observation classCode="OBS" moodCode="EVN">            <templateId root="2.16.840.1.113883.10.20.22.4.27"/>            <templateId root="2.16.840.1.113883.10.20.22.4.27" extension="2014-06-09"/>            <!-- Result observation template -->            <id root="b442a617-d457-b8fd-c14f-c67f73039121"/>        <code  code="72514-3" codeSystem="2.16.840.1.113883.6.1" displayName="Pain severity - 0-10 verbal numeric rating [Score] - Reported">          <originalText><reference value="#observations-desc-2"/></originalText>        </code>            <text>              <reference value="#observations-desc-2"/>            </text>            <statusCode code="completed"/>            <effectiveTime value="20250110005609"/>            <value xsi:type="PQ" value="1" unit="{score}"/>          </observation>        </component>        <component>          <observation classCode="OBS" moodCode="EVN">            <templateId root="2.16.840.1.113883.10.20.22.4.27"/>            <templateId root="2.16.840.1.113883.10.20.22.4.27" extension="2014-06-09"/>            <!-- Result observation template -->            <id root="b56939f3-26ae-cd5b-aebc-d39b73efd11c"/>        <code  code="29463-7" codeSystem="2.16.840.1.113883.6.1" displayName="Body Weight">          <originalText><reference value="#observations-desc-3"/></originalText>        </code>            <text>              <reference value="#observations-desc-3"/>            </text>            <statusCode code="completed"/>            <effectiveTime value="20250110005609"/>            <value xsi:type="PQ" value="65.8" unit="kg"/>          </observation>        </component>        <component>          <observation classCode="OBS" moodCode="EVN">            <templateId root="2.16.840.1.113883.10.20.22.4.27"/>            <templateId root="2.16.840.1.113883.10.20.22.4.27" extension="2014-06-09"/>            <!-- Result observation template -->            <id root="c8b69d66-4d3d-f6a5-dc2c-837f5b5d8a78"/>        <code  code="39156-5" codeSystem="2.16.840.1.113883.6.1" displayName="Body mass index (BMI) [Ratio]">          <originalText><reference value="#observations-desc-4"/></originalText>        </code>            <text>              <reference value="#observations-desc-4"/>            </text>            <statusCode code="completed"/>            <effectiveTime value="20250110005609"/>            <value xsi:type="PQ" value="22.82" unit="kg/m2"/>          </observation>        </component>        <component>          <observation classCode="OBS" moodCode="EVN">            <templateId root="2.16.840.1.113883.10.20.22.4.27"/>            <templateId root="2.16.840.1.113883.10.20.22.4.27" extension="2014-06-09"/>            <!-- Result observation template -->            <id root="4a1472e5-00c3-f614-bd97-a3018d9c8aa7"/>        <code  code="8867-4" codeSystem="2.16.840.1.113883.6.1" displayName="Heart rate">          <originalText><reference value="#observations-desc-5"/></originalText>        </code>            <text>              <reference value="#observations-desc-5"/>            </text>            <statusCode code="completed"/>            <effectiveTime value="20250110005609"/>            <value xsi:type="PQ" value="77" unit="/min"/>          </observation>        </component>        <component>          <observation classCode="OBS" moodCode="EVN">            <templateId root="2.16.840.1.113883.10.20.22.4.27"/>            <templateId root="2.16.840.1.113883.10.20.22.4.27" extension="2014-06-09"/>            <!-- Result observation template -->            <id root="d0779128-27e7-6521-8f3a-0380a9405767"/>        <code  code="9279-1" codeSystem="2.16.840.1.113883.6.1" displayName="Respiratory rate">          <originalText><reference value="#observations-desc-6"/></originalText>        </code>            <text>              <reference value="#observations-desc-6"/>            </text>            <statusCode code="completed"/>            <effectiveTime value="20250110005609"/>            <value xsi:type="PQ" value="14" unit="/min"/>          </observation>        </component>      </organizer>    </entry>  </section></component><component>  <!--Immunizations-->  <section>    <templateId root="2.16.840.1.113883.10.20.22.2.2" extension="2015-08-01"/>    <!--Immunizations section template-->    <code code="11369-6" codeSystem="2.16.840.1.113883.6.1" codeSystemName="LOINC" displayName="History of immunizations"/>    <title>Immunizations</title><text>  <table border="1" width="100%">    <thead>      <tr>        <th>Start</th>        <th>Stop</th>        <th>Description</th>        <th>Code</th>      </tr>    </thead>    <tbody>        <tr>          <td>2025-01-10T00:56:09Z</td>          <td></td>          <td ID="immunizations-desc-1">Influenza, seasonal, injectable, preservative free</td>          <td ID="immunizations-code-1">http://hl7.org/fhir/sid/cvx 140</td>        </tr>        <tr>          <td>2025-01-10T00:56:09Z</td>          <td></td>          <td ID="immunizations-desc-2">Td (adult), 5 Lf tetanus toxoid, preservative free, adsorbed</td>          <td ID="immunizations-code-2">http://hl7.org/fhir/sid/cvx 113</td>        </tr>        <tr>          <td>2025-01-10T00:56:09Z</td>          <td></td>          <td ID="immunizations-desc-3">Hep B, adult</td>          <td ID="immunizations-code-3">http://hl7.org/fhir/sid/cvx 43</td>        </tr>        <tr>          <td>2025-01-10T00:56:09Z</td>          <td></td>          <td ID="immunizations-desc-4">meningococcal MCV4P</td>          <td ID="immunizations-code-4">http://hl7.org/fhir/sid/cvx 114</td>        </tr>    </tbody>  </table></text>    <entry typeCode="DRIV">      <substanceAdministration classCode="SBADM" moodCode="EVN" negationInd="false">        <templateId root="2.16.840.1.113883.10.20.22.4.52"/>        <!-- Medication activity template -->        <id root="3badafbf-45b2-3e51-8356-8716446e4a5b"/>        <code code='IMMUNIZ' codeSystem='2.16.840.1.113883.5.4' codeSystemName='ActCode'/>        <text>          <reference value="#immunizations-desc-1"/>        </text>        <statusCode code="completed"/>        <effectiveTime value="20250110005609"/>        <doseQuantity nullFlavor="UNK"/>        <consumable>          <manufacturedProduct classCode="MANU">            <templateId root="2.16.840.1.113883.10.20.22.4.54"/>            <!-- Product template -->            <manufacturedMaterial>        <code  code="140" codeSystem="2.16.840.1.113883.12.292" displayName="Influenza, seasonal, injectable, preservative free">          <originalText><reference value="#immunizations-desc-1"/></originalText>        </code>              <name>Influenza, seasonal, injectable, preservative free</name>            </manufacturedMaterial>          </manufacturedProduct>        </consumable>      </substanceAdministration>    </entry>    <entry typeCode="DRIV">      <substanceAdministration classCode="SBADM" moodCode="EVN" negationInd="false">        <templateId root="2.16.840.1.113883.10.20.22.4.52"/>        <!-- Medication activity template -->        <id root="ecc9ce88-f899-c92b-d3e7-9b96eada4810"/>        <code code='IMMUNIZ' codeSystem='2.16.840.1.113883.5.4' codeSystemName='ActCode'/>        <text>          <reference value="#immunizations-desc-2"/>        </text>        <statusCode code="completed"/>        <effectiveTime value="20250110005609"/>        <doseQuantity nullFlavor="UNK"/>        <consumable>          <manufacturedProduct classCode="MANU">            <templateId root="2.16.840.1.113883.10.20.22.4.54"/>            <!-- Product template -->            <manufacturedMaterial>        <code  code="113" codeSystem="2.16.840.1.113883.12.292" displayName="Td (adult), 5 Lf tetanus toxoid, preservative free, adsorbed">          <originalText><reference value="#immunizations-desc-2"/></originalText>        </code>              <name>Td (adult), 5 Lf tetanus toxoid, preservative free, adsorbed</name>            </manufacturedMaterial>          </manufacturedProduct>        </consumable>      </substanceAdministration>    </entry>    <entry typeCode="DRIV">      <substanceAdministration classCode="SBADM" moodCode="EVN" negationInd="false">        <templateId root="2.16.840.1.113883.10.20.22.4.52"/>        <!-- Medication activity template -->        <id root="b9a3a3cf-db59-2208-1cb8-75b4861320aa"/>        <code code='IMMUNIZ' codeSystem='2.16.840.1.113883.5.4' codeSystemName='ActCode'/>        <text>          <reference value="#immunizations-desc-3"/>        </text>        <statusCode code="completed"/>        <effectiveTime value="20250110005609"/>        <doseQuantity nullFlavor="UNK"/>        <consumable>          <manufacturedProduct classCode="MANU">            <templateId root="2.16.840.1.113883.10.20.22.4.54"/>            <!-- Product template -->            <manufacturedMaterial>        <code  code="43" codeSystem="2.16.840.1.113883.12.292" displayName="Hep B, adult">          <originalText><reference value="#immunizations-desc-3"/></originalText>        </code>              <name>Hep B, adult</name>            </manufacturedMaterial>          </manufacturedProduct>        </consumable>      </substanceAdministration>    </entry>    <entry typeCode="DRIV">      <substanceAdministration classCode="SBADM" moodCode="EVN" negationInd="false">        <templateId root="2.16.840.1.113883.10.20.22.4.52"/>        <!-- Medication activity template -->        <id root="ebbe88b4-62f7-28ce-04fd-805c26451fcd"/>        <code code='IMMUNIZ' codeSystem='2.16.840.1.113883.5.4' codeSystemName='ActCode'/>        <text>          <reference value="#immunizations-desc-4"/>        </text>        <statusCode code="completed"/>        <effectiveTime value="20250110005609"/>        <doseQuantity nullFlavor="UNK"/>        <consumable>          <manufacturedProduct classCode="MANU">            <templateId root="2.16.840.1.113883.10.20.22.4.54"/>            <!-- Product template -->            <manufacturedMaterial>        <code  code="114" codeSystem="2.16.840.1.113883.12.292" displayName="meningococcal MCV4P">          <originalText><reference value="#immunizations-desc-4"/></originalText>        </code>              <name>meningococcal MCV4P</name>            </manufacturedMaterial>          </manufacturedProduct>        </consumable>      </substanceAdministration>    </entry>  </section></component><component>  <!--Plan of Care-->  <section>    <templateId root="2.16.840.1.113883.10.20.22.2.10"/>    <templateId root="2.16.840.1.113883.10.20.22.2.10" extension="2014-06-09"/>    <!--Plan of Care section template-->    <code code="18776-5" codeSystem="2.16.840.1.113883.6.1" codeSystemName="LOINC" displayName="Treatment plan"/>    <title>Plan of Care</title><text>  <table border="1" width="100%">    <thead>      <tr>        <th>Start</th>        <th>Stop</th>        <th>Description</th>        <th>Code</th>      </tr>    </thead>    <tbody>        <tr>          <td>2006-10-02T20:26:20Z</td>          <td></td>          <td ID="careplans-desc-1">Self-care interventions (procedure)</td>          <td ID="careplans-code-1">http://snomed.info/sct 384758001</td>        </tr>    </tbody>  </table></text>  </section></component><component>  <!--Social History - CCDA-->  <section>    <templateId root="2.16.840.1.113883.10.20.22.2.17" extension="2015-08-01"/>    <templateId root="2.16.840.1.113883.10.20.22.2.17"/>    <!-- Social history section template -->    <code code="29762-2" codeSystem="2.16.840.1.113883.6.1"/>    <title>Social History</title>    <text>There is no current social history except smoking status.</text>    <entry typeCode="DRIV">      <observation classCode="OBS" moodCode="EVN">        <templateId root="2.16.840.1.113883.10.20.22.4.78"/>        <templateId root="2.16.840.1.113883.10.20.22.4.78" extension="2014-06-09"/>        <!-- Smoking Status Meaningful Use template -->        <id root="8d9541ff-214f-57d4-845a-bcc26951db4c"/>        <code code="72166-2" codeSystem="2.16.840.1.113883.6.1" displayName="Tobacco smoking status NHIS" />        <statusCode code="completed"/>        <effectiveTime value="20250110005609"/>        <value xsi:type="CD" code="266919005" displayName="Never smoked tobacco (finding)" codeSystem="2.16.840.1.113883.6.96"/>          <author>            <time value="20250801005609"/>            <assignedAuthor>              <id nullFlavor="NA"/>              <addr nullFlavor="NA" />              <telecom nullFlavor="NA" />              <assignedAuthoringDevice>                <manufacturerModelName>https://github.com/synthetichealth/synthea</manufacturerModelName>                <softwareName>https://github.com/synthetichealth/synthea</softwareName>              </assignedAuthoringDevice>              <representedOrganization>                <id nullFlavor="NA"/>                <name>NEIGHBORHOOD HEALTH CENTER OF WNY, INC.</name>                <telecom nullFlavor="NA"/>                <addr>                  <streetAddressLine>155 LAWN AVE</streetAddressLine>                  <city>BUFFALO</city>                  <state>NY</state>                  <postalCode>142071816</postalCode>                </addr>              </representedOrganization>            </assignedAuthor>          </author>      </observation>    </entry>  </section></component><component><!--Survey Responses in Functional Status-->    <section>        <templateId root="2.16.840.1.113883.10.20.22.2.14" extension="2014-06-09" />        <templateId root="2.16.840.1.113883.10.20.22.2.14" />        <!-- Functional Status Section template V2-->        <code code="47420-5" codeSystem="2.16.840.1.113883.6.1" codeSystemName="LOINC" displayName="Functional Status" />        <title>Functional Status</title><text>  <table border="1" width="100%">    <thead>      <tr>        <th>Start</th>        <th>Stop</th>        <th>Description</th>        <th>Code</th>        <th>Value</th>      </tr>    </thead>    <tbody>        <tr>          <td>2025-01-10T02:11:52Z</td>          <td></td>          <td ID="functional-status-desc-1">Generalized anxiety disorder 7 item (GAD-7) total score [Reported.PHQ]</td>          <td ID="functional-status-code-1">http://loinc.org 70274-6</td>          <td>3 {score}</td>        </tr>    </tbody>  </table></text>        <entry>         <observation classCode="OBS" moodCode="EVN">             <templateId root="2.16.840.1.113883.10.20.22.4.69"/>             <id root="3cffd912-5776-c293-410d-9aeaf27d2dcc"/>        <code  code="70274-6" codeSystem="2.16.840.1.113883.6.1" displayName="Generalized anxiety disorder 7 item (GAD-7) total score [Reported.PHQ]">          <originalText><reference value="#functional-status-desc-1"/></originalText>        </code>             <text>               <reference value="#functional-status-desc-1"/>             </text>             <statusCode code="completed"/>             <effectiveTime value="20250110021152"/>             <value xsi:type="INT" value="3"/>         </observation>        </entry>    </section></component>    </structuredBody>  </component></ClinicalDocument>
